pyceptron/__init__.py
pyceptron/enums/middleware_training_monolayer.py
pyceptron/factivations/__init__.py
pyceptron/factivations/abs.py
pyceptron/factivations/base.py
pyceptron/factivations/elu.py
pyceptron/factivations/leaky_relu.py
pyceptron/factivations/linear.py
pyceptron/factivations/relu.py
pyceptron/factivations/sigmoid.py
pyceptron/factivations/tanh.py
pyceptron/objects/layers/layer.py
pyceptron/objects/layers/sequential.py
pyceptron/objects/perceptrons/models/fullbase.py
pyceptron/objects/perceptrons/models/perceptronABC.py
pyceptron/objects/perceptrons/pieces/base.py
pyceptron/objects/perceptrons/pieces/exporter.py
pyceptron/objects/perceptrons/pieces/trainers/classic.py
pyceptron/objects/perceptrons/pieces/trainers/gradient.py
pyceptron/objects/perceptrons/variants/classic.py
pyceptron/objects/perceptrons/variants/gradient.py
pyceptron/utils/__init__.py
pyceptron/utils/analyzer/__init__.py
pyceptron/utils/analyzer/abc_main.py
pyceptron/utils/analyzer/main.py
pyceptron/utils/generators/__init__.py
pyceptron/utils/generators/abs.py
pyceptron/utils/generators/base.py
pyceptron/utils/generators/main.py
pyceptron/utils/loaders/__init__.py
pyceptron/utils/loaders/perceptron.py
pyceptron-0.2.0.dist-info/METADATA
pyceptron-0.2.0.dist-info/WHEEL
pyceptron-0.2.0.dist-info/RECORD
