Metadata-Version: 2.1
Name: pyceptron
Version: 0.2.0
Summary: 🧠 Una librería que estudia a profundidad perceptrones multicapa y capas para el entrenamiento convencional de redes neuronales
License: MIT
Author: techatlasdev
Author-email: srgoqui@gmail.com
Requires-Python: >=3.12,<4.0
Classifier: License :: OSI Approved :: MIT License
Classifier: Programming Language :: Python :: 3
Classifier: Programming Language :: Python :: 3.12
Classifier: Programming Language :: Python :: 3.13
Requires-Dist: matplotlib (>=3.10.1,<4.0.0)
Requires-Dist: numpy (>=2.2.5,<3.0.0)
Requires-Dist: termpyx (>=0.1.0,<0.2.0)
